rubygems.py
rubygemsrecipe-0.2.2.dist-info/DESCRIPTION.rst
rubygemsrecipe-0.2.2.dist-info/top_level.txt
rubygemsrecipe-0.2.2.dist-info/metadata.json
rubygemsrecipe-0.2.2.dist-info/RECORD
rubygemsrecipe-0.2.2.dist-info/METADATA
rubygemsrecipe-0.2.2.dist-info/WHEEL
rubygemsrecipe-0.2.2.dist-info/entry_points.txt
