Metadata-Version: 2.0
Name: rubygemsrecipe
Version: 0.2.2
Summary: zc.buildout recipe for installing ruby gems.
Home-page: https://bitbucket.org/sirex/rubygemsrecipe
Author: Mantas Zimnickas
Author-email: sirexas@gmail.com
License: GPL
Platform: UNKNOWN
Classifier: Framework :: Buildout
Classifier: Intended Audience :: Developers
Classifier: License :: OSI Approved :: GNU General Public License (GPL)
Classifier: Topic :: Software Development :: Libraries :: Ruby Modules
Classifier: Programming Language :: Python :: 2
Classifier: Programming Language :: Python :: 3
Requires-Dist: six
Requires-Dist: zc.buildout
Requires-Dist: setuptools
Requires-Dist: hexagonit.recipe.download
